{
  "captured_at": "2025-09-30T09:43:02.858Z",
  "reserve_height": 248504,
  "previous_height": 248503,
  "hf_version": 3,
  "on_chain": {
    "zeph_reserve_atoms": "1117241089836585320",
    "zeph_reserve": 1117241.0898365853,
    "zsd_circ_atoms": "1033089784210551827",
    "zsd_circ": 1033089.7842105518,
    "zrs_circ_atoms": "713719948549502381",
    "zrs_circ": 713719.9485495023,
    "zyield_circ_atoms": "0",
    "zyield_circ": 0,
    "zsd_yield_reserve_atoms": "0",
    "zsd_yield_reserve": 0,
    "reserve_ratio_atoms": "8.574659",
    "reserve_ratio": 8.574659,
    "reserve_ratio_ma_atoms": "8.836800",
    "reserve_ratio_ma": 8.8368
  },
  "pricing_record": {
    "moving_average": 8171206440000,
    "reserve": 1382815070000,
    "reserve_ma": 1388230610000,
    "reserve_ratio": 0,
    "reserve_ratio_ma": 0,
    "signature": "07e062388e4d28820c6d3bd6e0c952b2cc4dd2a4fec4a0117ed1076a35a0e45d301cfc5e7d986db68693e3cc0fb1789ed319699e1426b080a978e11aef99ea86",
    "spot": 7928810550000,
    "stable": 126122320000,
    "stable_ma": 122380940000,
    "timestamp": 1715412925,
    "yield_price": 0
  },
  "raw": {
    "assets": "8858392939989815461",
    "assets_ma": "9129207588305324514",
    "equity": "7825303155779263634",
    "equity_ma": "8096117804094772687",
    "height": 248504,
    "hf_version": 3,
    "liabilities": "1033089784210551827",
    "num_reserves": "713719948549502381",
    "num_stables": "1033089784210551827",
    "num_zyield": "0",
    "pr": {
      "moving_average": 8171206440000,
      "reserve": 1382815070000,
      "reserve_ma": 1388230610000,
      "reserve_ratio": 0,
      "reserve_ratio_ma": 0,
      "signature": "07e062388e4d28820c6d3bd6e0c952b2cc4dd2a4fec4a0117ed1076a35a0e45d301cfc5e7d986db68693e3cc0fb1789ed319699e1426b080a978e11aef99ea86",
      "spot": 7928810550000,
      "stable": 126122320000,
      "stable_ma": 122380940000,
      "timestamp": 1715412925,
      "yield_price": 0
    },
    "reserve_ratio": "8.574659",
    "reserve_ratio_ma": "8.836800",
    "status": "OK",
    "zeph_reserve": "1117241089836585320",
    "zyield_reserve": "0"
  }
}